{
  "fetched_at": "2026-07-22T02:56:33.009933+00:00",
  "companies": [
    {
      "no": "1",
      "ticker": "AAEM",
      "company": "Agnico Eagle Mines Ltd",
      "sector": "Basic Materials",
      "industry": "Gold",
      "country": "Canada",
      "market_cap": "72.15B",
      "pe": "13.32",
      "price": "141.62",
      "change": "3.87%",
      "volume": "2,901,797"
    },
    {
      "no": "2",
      "ticker": "AAGCO",
      "company": "AGCO Corp",
      "sector": "Industrials",
      "industry": "Farm & Heavy Construction Machinery",
      "country": "USA",
      "market_cap": "8.09B",
      "pe": "10.79",
      "price": "111.79",
      "change": "-0.48%",
      "volume": "615,874"
    },
    {
      "no": "3",
      "ticker": "AAGI",
      "company": "Alamos Gold Inc",
      "sector": "Basic Materials",
      "industry": "Gold",
      "country": "Canada",
      "market_cap": "12.40B",
      "pe": "11.74",
      "price": "29.52",
      "change": "4.79%",
      "volume": "3,254,754"
    },
    {
      "no": "4",
      "ticker": "AALV",
      "company": "Autoliv Inc",
      "sector": "Consumer Cyclical",
      "industry": "Auto Parts",
      "country": "Sweden",
      "market_cap": "8.61B",
      "pe": "13.84",
      "price": "117.51",
      "change": "0.24%",
      "volume": "1,207,187"
    },
    {
      "no": "5",
      "ticker": "AAMG",
      "company": "Affiliated Managers Group Inc",
      "sector": "Financial",
      "industry": "Asset Management",
      "country": "USA",
      "market_cap": "9.00B",
      "pe": "13.88",
      "price": "340.58",
      "change": "-6.98%",
      "volume": "910,264"
    },
    {
      "no": "6",
      "ticker": "AAMP",
      "company": "Ameriprise Financial Inc",
      "sector": "Financial",
      "industry": "Asset Management",
      "country": "USA",
      "market_cap": "47.50B",
      "pe": "13.14",
      "price": "528.37",
      "change": "0.41%",
      "volume": "557,118"
    },
    {
      "no": "7",
      "ticker": "AASR",
      "company": "Grupo Aeroportuario Del Sureste SA ADR",
      "sector": "Industrials",
      "industry": "Airports & Air Services",
      "country": "Mexico",
      "market_cap": "7.62B",
      "pe": "15.51",
      "price": "274.96",
      "change": "0.22%",
      "volume": "48,972"
    },
    {
      "no": "8",
      "ticker": "AAU",
      "company": "AngloGold Ashanti Plc",
      "sector": "Basic Materials",
      "industry": "Gold",
      "country": "USA",
      "market_cap": "39.64B",
      "pe": "11.52",
      "price": "78.50",
      "change": "4.83%",
      "volume": "2,250,850"
    },
    {
      "no": "9",
      "ticker": "BB",
      "company": "Barrick Mining Corp",
      "sector": "Basic Materials",
      "industry": "Gold",
      "country": "Canada",
      "market_cap": "60.94B",
      "pe": "10.02",
      "price": "36.37",
      "change": "4.24%",
      "volume": "7,500,168"
    },
    {
      "no": "10",
      "ticker": "BBAP",
      "company": "Credicorp Ltd",
      "sector": "Financial",
      "industry": "Banks - Regional",
      "country": "Peru",
      "market_cap": "31.11B",
      "pe": "15.03",
      "price": "391.10",
      "change": "1.10%",
      "volume": "280,607"
    },
    {
      "no": "11",
      "ticker": "CCGAU",
      "company": "Centerra Gold Inc",
      "sector": "Basic Materials",
      "industry": "Gold",
      "country": "Canada",
      "market_cap": "3.19B",
      "pe": "5.17",
      "price": "16.05",
      "change": "5.66%",
      "volume": "1,043,394"
    },
    {
      "no": "12",
      "ticker": "CCINT",
      "company": "CI&T Inc",
      "sector": "Technology",
      "industry": "Software - Infrastructure",
      "country": "Brazil",
      "market_cap": "413.20M",
      "pe": "10.35",
      "price": "3.21",
      "change": "-1.23%",
      "volume": "133,394"
    },
    {
      "no": "13",
      "ticker": "CCMCL",
      "company": "Caledonia Mining Corp Plc",
      "sector": "Basic Materials",
      "industry": "Gold",
      "country": "United Kingdom",
      "market_cap": "353.06M",
      "pe": "5.70",
      "price": "18.26",
      "change": "8.76%",
      "volume": "265,992"
    },
    {
      "no": "14",
      "ticker": "CCPRX",
      "company": "Catalyst Pharmaceuticals Inc",
      "sector": "Healthcare",
      "industry": "Biotechnology",
      "country": "USA",
      "market_cap": "3.86B",
      "pe": "18.10",
      "price": "31.49",
      "change": "0.00%",
      "volume": "0"
    },
    {
      "no": "15",
      "ticker": "CCUVL",
      "company": "Clinuvel Pharmaceuticals Ltd ADR",
      "sector": "Healthcare",
      "industry": "Biotechnology",
      "country": "Australia",
      "market_cap": "353.88M",
      "pe": "17.00",
      "price": "7.02",
      "change": "-5.14%",
      "volume": "6,259"
    },
    {
      "no": "16",
      "ticker": "CCVSA",
      "company": "Covista Inc",
      "sector": "Consumer Defensive",
      "industry": "Education & Training Services",
      "country": "USA",
      "market_cap": "3.96B",
      "pe": "19.63",
      "price": "116.35",
      "change": "1.14%",
      "volume": "369,515"
    },
    {
      "no": "17",
      "ticker": "DDECK",
      "company": "Deckers Outdoor Corp",
      "sector": "Consumer Cyclical",
      "industry": "Footwear & Accessories",
      "country": "USA",
      "market_cap": "14.35B",
      "pe": "14.68",
      "price": "103.31",
      "change": "-0.70%",
      "volume": "2,339,161"
    },
    {
      "no": "18",
      "ticker": "DDRD",
      "company": "DRDGold Ltd ADR",
      "sector": "Basic Materials",
      "industry": "Gold",
      "country": "South Africa",
      "market_cap": "1.79B",
      "pe": "9.99",
      "price": "20.72",
      "change": "5.45%",
      "volume": "291,909"
    },
    {
      "no": "19",
      "ticker": "EEG",
      "company": "Everest Group Ltd",
      "sector": "Financial",
      "industry": "Insurance - Reinsurance",
      "country": "Bermuda",
      "market_cap": "14.92B",
      "pe": "7.68",
      "price": "377.09",
      "change": "-0.50%",
      "volume": "426,785"
    },
    {
      "no": "20",
      "ticker": "EEGO",
      "company": "Eldorado Gold Corp",
      "sector": "Basic Materials",
      "industry": "Gold",
      "country": "Canada",
      "market_cap": "7.95B",
      "pe": "10.78",
      "price": "30.46",
      "change": "9.84%",
      "volume": "3,191,001"
    },
    {
      "no": "21",
      "ticker": "EERO",
      "company": "Ero Copper Corp",
      "sector": "Basic Materials",
      "industry": "Copper",
      "country": "Canada",
      "market_cap": "2.80B",
      "pe": "9.61",
      "price": "26.87",
      "change": "7.05%",
      "volume": "1,324,991"
    },
    {
      "no": "22",
      "ticker": "EEVR",
      "company": "Evercore Inc",
      "sector": "Financial",
      "industry": "Capital Markets",
      "country": "USA",
      "market_cap": "13.17B",
      "pe": "19.21",
      "price": "340.52",
      "change": "2.10%",
      "volume": "458,692"
    },
    {
      "no": "23",
      "ticker": "EEXEL",
      "company": "Exelixis Inc",
      "sector": "Healthcare",
      "industry": "Biotechnology",
      "country": "USA",
      "market_cap": "14.11B",
      "pe": "18.60",
      "price": "56.12",
      "change": "1.06%",
      "volume": "1,820,120"
    },
    {
      "no": "24",
      "ticker": "EEXLS",
      "company": "ExlService Holdings Inc",
      "sector": "Technology",
      "industry": "Information Technology Services",
      "country": "USA",
      "market_cap": "4.18B",
      "pe": "17.45",
      "price": "27.35",
      "change": "-2.96%",
      "volume": "1,730,951"
    },
    {
      "no": "25",
      "ticker": "FFSLR",
      "company": "First Solar Inc",
      "sector": "Technology",
      "industry": "Solar",
      "country": "USA",
      "market_cap": "22.14B",
      "pe": "13.31",
      "price": "206.05",
      "change": "0.36%",
      "volume": "1,742,134"
    },
    {
      "no": "26",
      "ticker": "FFSM",
      "company": "Fortuna Mining Corp",
      "sector": "Basic Materials",
      "industry": "Gold",
      "country": "Canada",
      "market_cap": "2.57B",
      "pe": "7.87",
      "price": "8.47",
      "change": "5.48%",
      "volume": "4,012,466"
    },
    {
      "no": "27",
      "ticker": "GG",
      "company": "Genpact Ltd",
      "sector": "Technology",
      "industry": "Information Technology Services",
      "country": "Bermuda",
      "market_cap": "5.12B",
      "pe": "9.28",
      "price": "30.18",
      "change": "-1.50%",
      "volume": "1,477,088"
    },
    {
      "no": "28",
      "ticker": "GGFI",
      "company": "Gold Fields Ltd ADR",
      "sector": "Basic Materials",
      "industry": "Gold",
      "country": "South Africa",
      "market_cap": "28.90B",
      "pe": "8.17",
      "price": "32.29",
      "change": "3.33%",
      "volume": "2,509,063"
    },
    {
      "no": "29",
      "ticker": "GGMED",
      "company": "Globus Medical Inc",
      "sector": "Healthcare",
      "industry": "Medical Devices",
      "country": "USA",
      "market_cap": "10.32B",
      "pe": "17.72",
      "price": "76.09",
      "change": "0.11%",
      "volume": "1,155,930"
    },
    {
      "no": "30",
      "ticker": "HHLNE",
      "company": "Hamilton Lane Inc",
      "sector": "Financial",
      "industry": "Asset Management",
      "country": "USA",
      "market_cap": "4.68B",
      "pe": "14.24",
      "price": "84.28",
      "change": "-0.38%",
      "volume": "571,614"
    },
    {
      "no": "31",
      "ticker": "IIAG",
      "company": "Iamgold Corp",
      "sector": "Basic Materials",
      "industry": "Gold",
      "country": "Canada",
      "market_cap": "8.65B",
      "pe": "8.73",
      "price": "14.96",
      "change": "7.16%",
      "volume": "4,777,971"
    },
    {
      "no": "32",
      "ticker": "IIBEX",
      "company": "IBEX Ltd",
      "sector": "Technology",
      "industry": "Information Technology Services",
      "country": "USA",
      "market_cap": "467.82M",
      "pe": "10.90",
      "price": "34.94",
      "change": "-0.37%",
      "volume": "98,228"
    },
    {
      "no": "33",
      "ticker": "IIDT",
      "company": "IDT Corp",
      "sector": "Communication Services",
      "industry": "Telecom Services",
      "country": "USA",
      "market_cap": "1.58B",
      "pe": "19.43",
      "price": "63.35",
      "change": "0.49%",
      "volume": "152,749"
    },
    {
      "no": "34",
      "ticker": "IINTU",
      "company": "Intuit Inc",
      "sector": "Technology",
      "industry": "Software - Application",
      "country": "USA",
      "market_cap": "79.30B",
      "pe": "17.56",
      "price": "289.92",
      "change": "-1.33%",
      "volume": "3,176,585"
    },
    {
      "no": "35",
      "ticker": "IITRN",
      "company": "Ituran Location And Control Ltd",
      "sector": "Technology",
      "industry": "Scientific & Technical Instruments",
      "country": "Israel",
      "market_cap": "1.14B",
      "pe": "18.96",
      "price": "57.43",
      "change": "3.09%",
      "volume": "427,768"
    },
    {
      "no": "36",
      "ticker": "KKGC",
      "company": "Kinross Gold Corp",
      "sector": "Basic Materials",
      "industry": "Gold",
      "country": "Canada",
      "market_cap": "27.95B",
      "pe": "9.92",
      "price": "23.41",
      "change": "3.91%",
      "volume": "7,081,481"
    },
    {
      "no": "37",
      "ticker": "KKSPI",
      "company": "Kaspi.kz JSC ADR",
      "sector": "Technology",
      "industry": "Software - Infrastructure",
      "country": "Kazakhstan",
      "market_cap": "16.93B",
      "pe": "8.27",
      "price": "89.08",
      "change": "1.06%",
      "volume": "156,071"
    },
    {
      "no": "38",
      "ticker": "LLRN",
      "company": "Stride Inc",
      "sector": "Consumer Defensive",
      "industry": "Education & Training Services",
      "country": "USA",
      "market_cap": "3.60B",
      "pe": "13.06",
      "price": "84.69",
      "change": "-1.11%",
      "volume": "521,919"
    },
    {
      "no": "39",
      "ticker": "LLX",
      "company": "LexinFintech Holdings Ltd ADR",
      "sector": "Financial",
      "industry": "Credit Services",
      "country": "China",
      "market_cap": "190.93M",
      "pe": "1.25",
      "price": "1.44",
      "change": "-0.69%",
      "volume": "2,610,100"
    },
    {
      "no": "40",
      "ticker": "MMCRI",
      "company": "Monarch Casino & Resort Inc",
      "sector": "Consumer Cyclical",
      "industry": "Resorts & Casinos",
      "country": "USA",
      "market_cap": "2.08B",
      "pe": "18.86",
      "price": "117.45",
      "change": "-5.57%",
      "volume": "280,437"
    },
    {
      "no": "41",
      "ticker": "MMLI",
      "company": "Mueller Industries Inc",
      "sector": "Industrials",
      "industry": "Metal Fabrication",
      "country": "USA",
      "market_cap": "13.78B",
      "pe": "16.33",
      "price": "62.30",
      "change": "5.65%",
      "volume": "1,907,762"
    },
    {
      "no": "42",
      "ticker": "NNEM",
      "company": "Newmont Corp",
      "sector": "Basic Materials",
      "industry": "Gold",
      "country": "USA",
      "market_cap": "98.74B",
      "pe": "12.00",
      "price": "92.49",
      "change": "3.69%",
      "volume": "8,045,527"
    },
    {
      "no": "43",
      "ticker": "NNRDS",
      "company": "Nerdwallet Inc",
      "sector": "Communication Services",
      "industry": "Internet Content & Information",
      "country": "USA",
      "market_cap": "600.08M",
      "pe": "9.79",
      "price": "9.12",
      "change": "-0.55%",
      "volume": "517,525"
    },
    {
      "no": "44",
      "ticker": "NNTB",
      "company": "Bank of N T Butterfield & Son Ltd",
      "sector": "Financial",
      "industry": "Banks - Diversified",
      "country": "Bermuda",
      "market_cap": "2.44B",
      "pe": "10.59",
      "price": "61.15",
      "change": "0.49%",
      "volume": "148,178"
    },
    {
      "no": "45",
      "ticker": "NNTES",
      "company": "NetEase Inc ADR",
      "sector": "Communication Services",
      "industry": "Electronic Gaming & Multimedia",
      "country": "China",
      "market_cap": "82.71B",
      "pe": "17.35",
      "price": "129.55",
      "change": "-3.46%",
      "volume": "1,378,316"
    },
    {
      "no": "46",
      "ticker": "OOSK",
      "company": "Oshkosh Corp",
      "sector": "Industrials",
      "industry": "Farm & Heavy Construction Machinery",
      "country": "USA",
      "market_cap": "9.13B",
      "pe": "16.31",
      "price": "146.40",
      "change": "3.10%",
      "volume": "483,085"
    },
    {
      "no": "47",
      "ticker": "PPAAS",
      "company": "Pan American Silver Corp",
      "sector": "Basic Materials",
      "industry": "Gold",
      "country": "Canada",
      "market_cap": "18.72B",
      "pe": "14.24",
      "price": "44.43",
      "change": "5.31%",
      "volume": "4,621,452"
    },
    {
      "no": "48",
      "ticker": "PPAYC",
      "company": "Paycom Software Inc",
      "sector": "Technology",
      "industry": "Software - Application",
      "country": "USA",
      "market_cap": "6.87B",
      "pe": "16.67",
      "price": "144.22",
      "change": "-3.67%",
      "volume": "682,827"
    },
    {
      "no": "49",
      "ticker": "PPLGO",
      "company": "Pelagos Insurance Capital Ltd",
      "sector": "Financial",
      "industry": "Insurance - Diversified",
      "country": "Bermuda",
      "market_cap": "2.19B",
      "pe": "6.83",
      "price": "25.56",
      "change": "-0.08%",
      "volume": "246,247"
    },
    {
      "no": "50",
      "ticker": "PPLMR",
      "company": "Palomar Holdings Inc",
      "sector": "Financial",
      "industry": "Insurance - Property & Casualty",
      "country": "USA",
      "market_cap": "3.61B",
      "pe": "18.97",
      "price": "136.34",
      "change": "-2.70%",
      "volume": "204,667"
    },
    {
      "no": "51",
      "ticker": "PPUK",
      "company": "Prudential plc ADR",
      "sector": "Financial",
      "industry": "Insurance - Life",
      "country": "Hong Kong",
      "market_cap": "35.98B",
      "pe": "9.41",
      "price": "28.88",
      "change": "2.16%",
      "volume": "941,009"
    },
    {
      "no": "52",
      "ticker": "RRJF",
      "company": "Raymond James Financial Inc",
      "sector": "Financial",
      "industry": "Asset Management",
      "country": "USA",
      "market_cap": "32.73B",
      "pe": "15.88",
      "price": "167.93",
      "change": "-0.23%",
      "volume": "1,511,824"
    },
    {
      "no": "53",
      "ticker": "RRMD",
      "company": "Resmed Inc",
      "sector": "Healthcare",
      "industry": "Medical Instruments & Supplies",
      "country": "USA",
      "market_cap": "28.40B",
      "pe": "18.88",
      "price": "195.80",
      "change": "-1.41%",
      "volume": "1,112,989"
    },
    {
      "no": "54",
      "ticker": "SSCHW",
      "company": "Charles Schwab Corp",
      "sector": "Financial",
      "industry": "Capital Markets",
      "country": "USA",
      "market_cap": "173.84B",
      "pe": "19.82",
      "price": "99.96",
      "change": "-2.52%",
      "volume": "14,815,081"
    },
    {
      "no": "55",
      "ticker": "SSEIC",
      "company": "SEI Investments Co",
      "sector": "Financial",
      "industry": "Asset Management",
      "country": "USA",
      "market_cap": "11.74B",
      "pe": "16.66",
      "price": "97.65",
      "change": "-1.73%",
      "volume": "866,846"
    },
    {
      "no": "56",
      "ticker": "TTAYD",
      "company": "Taylor Devices Inc",
      "sector": "Industrials",
      "industry": "Specialty Industrial Machinery",
      "country": "USA",
      "market_cap": "181.70M",
      "pe": "17.84",
      "price": "56.44",
      "change": "2.96%",
      "volume": "89,181"
    },
    {
      "no": "57",
      "ticker": "TTFPM",
      "company": "Triple Flag Precious Metals Corp",
      "sector": "Basic Materials",
      "industry": "Other Precious Metals & Mining",
      "country": "Canada",
      "market_cap": "5.89B",
      "pe": "18.87",
      "price": "28.52",
      "change": "4.13%",
      "volume": "430,095"
    },
    {
      "no": "58",
      "ticker": "TTIMB",
      "company": "TIM SA ADR",
      "sector": "Communication Services",
      "industry": "Telecom Services",
      "country": "Brazil",
      "market_cap": "10.63B",
      "pe": "13.46",
      "price": "22.26",
      "change": "0.09%",
      "volume": "211,363"
    },
    {
      "no": "59",
      "ticker": "TTTAM",
      "company": "Titan America SA",
      "sector": "Basic Materials",
      "industry": "Building Materials",
      "country": "Belgium",
      "market_cap": "3.11B",
      "pe": "16.83",
      "price": "16.89",
      "change": "0.78%",
      "volume": "155,049"
    },
    {
      "no": "60",
      "ticker": "UULTA",
      "company": "Ulta Beauty Inc",
      "sector": "Consumer Cyclical",
      "industry": "Specialty Retail",
      "country": "USA",
      "market_cap": "21.04B",
      "pe": "18.35",
      "price": "489.47",
      "change": "0.28%",
      "volume": "745,009"
    },
    {
      "no": "61",
      "ticker": "UUTHR",
      "company": "United Therapeutics Corp",
      "sector": "Healthcare",
      "industry": "Drug Manufacturers - Specialty & Generic",
      "country": "USA",
      "market_cap": "22.74B",
      "pe": "19.78",
      "price": "535.83",
      "change": "1.23%",
      "volume": "467,386"
    },
    {
      "no": "62",
      "ticker": "WWTW",
      "company": "Willis Towers Watson Public Limited Co",
      "sector": "Financial",
      "industry": "Insurance Brokers",
      "country": "United Kingdom",
      "market_cap": "27.28B",
      "pe": "16.91",
      "price": "288.82",
      "change": "-1.53%",
      "volume": "405,375"
    },
    {
      "no": "63",
      "ticker": "ZZTO",
      "company": "ZTO Express (Cayman) Inc ADR",
      "sector": "Industrials",
      "industry": "Integrated Freight & Logistics",
      "country": "China",
      "market_cap": "13.45B",
      "pe": "15.00",
      "price": "24.00",
      "change": "-0.62%",
      "volume": "1,303,739"
    }
  ]
}